dicemaths/__init__.py
dicemaths/core.py
dicemaths/coreMaths.py
dicemaths/infinity.py
dicemaths/infinityMaths.py
tests/__init__.py
tests/test_infinity.py
dicemaths-0.3.0.dist-info/LICENSE
dicemaths-0.3.0.dist-info/METADATA
dicemaths-0.3.0.dist-info/WHEEL
dicemaths-0.3.0.dist-info/top_level.txt
dicemaths-0.3.0.dist-info/RECORD
