Metadata-Version: 2.1
Name: dicemaths
Version: 0.3.0
Summary: Package for performing basic statistical calculations on the outcomes of dice rolls
Home-page: https://github.com/AlDacMac/dicemaths
Author: AlDacMac
Author-email: alasdairmacgdev@gmail.com
License: UNKNOWN
Platform: UNKNOWN
Classifier: Programming Language :: Python :: 3
Classifier: License :: OSI Approved :: MIT License
Classifier: Operating System :: OS Independent
